README
flask_sixpack.py
setup.py
Flask_Sixpack.egg-info/PKG-INFO
Flask_Sixpack.egg-info/SOURCES.txt
Flask_Sixpack.egg-info/dependency_links.txt
Flask_Sixpack.egg-info/not-zip-safe
Flask_Sixpack.egg-info/requires.txt
Flask_Sixpack.egg-info/top_level.txt