Metadata-Version: 1.0
Name: Flask-Sixpack
Version: 0.0.1
Summary: Flask wrapper for Sixpack
Home-page: http://sixpack.seatgeek.com/
Author: Zack Kitzmiller
Author-email: Zack Kitzmiller
License: BSD
Platform: any
Classifier: Environment :: Web Environment
Classifier: Intended Audience :: Developers
Classifier: License :: OSI Approved :: BSD License
Classifier: Operating System :: OS Independent
Classifier: Programming Language :: Python
Classifier: Topic :: Internet :: WWW/HTTP :: Dynamic Content
Classifier: Topic :: Software Development :: Libraries :: Python Modules
